LICENSE
LICENSE.txt
MANIFEST.in
README.data_import.txt
README.md
database.sqlite
setup.py
scripts/insert_aliases.py
scripts/insert_figures.py
scripts/insert_results.py
scripts/insert_supplementary_data.py
scripts/insert_zscores.py
scripts/tigreServer.py
tigreBrowser/__init__.py
tigreBrowser/browser_utils.py
tigreBrowser/database.py
tigreBrowser/database_import.py
tigreBrowser/results.py
tigreBrowser.egg-info/PKG-INFO
tigreBrowser.egg-info/SOURCES.txt
tigreBrowser.egg-info/dependency_links.txt
tigreBrowser.egg-info/requires.txt
tigreBrowser.egg-info/top_level.txt
tigreBrowser/cgi/tigreBrowser/imagehelper.cgi
tigreBrowser/cgi/tigreBrowser/jquery-1.4.2.min.js
tigreBrowser/cgi/tigreBrowser/jquery-dynamic-form.js
tigreBrowser/cgi/tigreBrowser/tigreBrowser.cfg
tigreBrowser/cgi/tigreBrowser/tigreBrowser.cgi
tigreBrowser/cgi/tigreBrowser/tigreBrowser.css
tigreBrowser/cgi/tigreBrowser/tigreBrowser.js
tigreBrowser/cgi/tigreBrowser.new/imagehelper.cgi
tigreBrowser/cgi/tigreBrowser.new/jquery-1.4.2.min.js
tigreBrowser/cgi/tigreBrowser.new/jquery-dynamic-form.js
tigreBrowser/cgi/tigreBrowser.new/tigreBrowser.cfg
tigreBrowser/cgi/tigreBrowser.new/tigreBrowser.cgi
tigreBrowser/cgi/tigreBrowser.new/tigreBrowser.css
tigreBrowser/cgi/tigreBrowser.new/tigreBrowser.js