Metadata-Version: 1.1
Name: tigreBrowser
Version: 1.1
Summary: Gene expression model browser for results from tigre R package (http://www.bioconductor.org/packages/release/bioc/html/tigre.html)
Home-page: https://github.com/PROBIC/tigreBrowser/
Author: Antti Honkela
Author-email: antti.honkela@helsinki.fi
License: AGPL3
Platform: UNKNOWN
Classifier: Environment :: Web Environment
Classifier: License :: OSI Approved :: GNU Affero General Public License v3
Classifier: Natural Language :: English
Classifier: Operating System :: OS Independent
Classifier: Programming Language :: Python
Classifier: Topic :: Database :: Front-Ends
Classifier: Topic :: Internet :: WWW/HTTP :: Dynamic Content
Classifier: Topic :: Scientific/Engineering :: Bio-Informatics
